[
	{"drawDate": "04-01-2024", "one" : "02*03", "two" : "21*28", "three" : "34*31"},
	{"drawDate": "04-02-2024", "one" : "10*13", "two" : "35*27", "three" : "17*03"},
	{"drawDate": "04-03-2024", "one" : "26*17", "two" : "09*08", "three" : "06*29"},
	{"drawDate": "04-04-2024", "one" : "27*07", "two" : "32*14", "three" : "39*01"},
	{"drawDate": "04-05-2024", "one" : "26*37", "two" : "06*13", "three" : "04*02"},
	{"drawDate": "04-06-2024", "one" : "10*06", "two" : "36*20", "three" : "07*01"},
	{"drawDate": "04-07-2024", "one" : "01*04", "two" : "08*14", "three" : "31*28"},
	{"drawDate": "04-08-2024", "one" : "13*15", "two" : "02*27", "three" : "12*12"},
	{"drawDate": "04-09-2024", "one" : "02*30", "two" : "24*17", "three" : "33*32"},
	{"drawDate": "04-10-2024", "one" : "19*39", "two" : "05*40", "three" : "34*38"},
	{"drawDate": "04-11-2024", "one" : "24*07", "two" : "34*23", "three" : "23*23"},
	{"drawDate": "04-12-2024", "one" : "30*31", "two" : "40*06", "three" : "22*01"},
	{"drawDate": "04-13-2024", "one" : "06*03", "two" : "35*17", "three" : "26*39"},
	{"drawDate": "04-14-2024", "one" : "06*40", "two" : "14*37", "three" : "20*05"},
	{"drawDate": "04-15-2024", "one" : "33*17", "two" : "36*11", "three" : "21*11"},
	{"drawDate": "04-16-2024", "one" : "30*29", "two" : "02*16", "three" : "11*30"},
	{"drawDate": "04-17-2024", "one" : "40*17", "two" : "38*20", "three" : "31*05"},
	{"drawDate": "04-18-2024", "one" : "26*34", "two" : "19*19", "three" : "12*34"},
	{"drawDate": "04-19-2024", "one" : "05*36", "two" : "34*02", "three" : "36*03"},
	{"drawDate": "04-20-2024", "one" : "19*35", "two" : "19*07", "three" : "25*06"},
	{"drawDate": "04-21-2024", "one" : "26*13", "two" : "38*39", "three" : "01*07"},
	{"drawDate": "04-22-2024", "one" : "05*22", "two" : "38*25", "three" : "38*10"},
	{"drawDate": "04-23-2024", "one" : "38*13", "two" : "01*22", "three" : "25*21"},
	{"drawDate": "04-24-2024", "one" : "26*26", "two" : "18*30", "three" : "36*24"},
	{"drawDate": "04-25-2024", "one" : "31*11", "two" : "27*02", "three" : "38*28"},
	{"drawDate": "04-26-2024", "one" : "34*40", "two" : "30*17", "three" : "03*06"},
	{"drawDate": "04-27-2024", "one" : "04*21", "two" : "", "three" : ""}
]
